MdnWenjianApiZhongwenWendang/README.md
MdnWenjianApiZhongwenWendang/__init__.py
MdnWenjianApiZhongwenWendang/__main__.py
MdnWenjianApiZhongwenWendang/file.epub
MdnWenjianApiZhongwenWendang/index.html
MdnWenjianApiZhongwenWendang/css/__init__.py
MdnWenjianApiZhongwenWendang/css/annotations.css
MdnWenjianApiZhongwenWendang/css/main.css
MdnWenjianApiZhongwenWendang/css/normalize.css
MdnWenjianApiZhongwenWendang/css/popup.css
MdnWenjianApiZhongwenWendang/font/__init__.py
MdnWenjianApiZhongwenWendang/font/fontello.eot
MdnWenjianApiZhongwenWendang/font/fontello.svg
MdnWenjianApiZhongwenWendang/font/fontello.ttf
MdnWenjianApiZhongwenWendang/font/fontello.woff
MdnWenjianApiZhongwenWendang/img/__init__.py
MdnWenjianApiZhongwenWendang/img/annotator-glyph-sprite.png
MdnWenjianApiZhongwenWendang/img/annotator-icon-sprite.png
MdnWenjianApiZhongwenWendang/img/apple-touch-icon.png
MdnWenjianApiZhongwenWendang/img/cancelfullscreen.png
MdnWenjianApiZhongwenWendang/img/close.png
MdnWenjianApiZhongwenWendang/img/fullscreen.png
MdnWenjianApiZhongwenWendang/img/loader.gif
MdnWenjianApiZhongwenWendang/img/menu-icon.png
MdnWenjianApiZhongwenWendang/img/save.png
MdnWenjianApiZhongwenWendang/img/saved.png
MdnWenjianApiZhongwenWendang/img/settings-s.png
MdnWenjianApiZhongwenWendang/img/settings.png
MdnWenjianApiZhongwenWendang/img/star.png
MdnWenjianApiZhongwenWendang/js/__init__.py
MdnWenjianApiZhongwenWendang/js/epub.js
MdnWenjianApiZhongwenWendang/js/epub.min.js
MdnWenjianApiZhongwenWendang/js/epub.min.map
MdnWenjianApiZhongwenWendang/js/hooks.min.js
MdnWenjianApiZhongwenWendang/js/hooks.min.map
MdnWenjianApiZhongwenWendang/js/reader.js
MdnWenjianApiZhongwenWendang/js/reader.js.map
MdnWenjianApiZhongwenWendang/js/reader.min.js
MdnWenjianApiZhongwenWendang/js/reader.min.map
MdnWenjianApiZhongwenWendang/js/hooks/__init__.py
MdnWenjianApiZhongwenWendang/js/hooks/extensions/__init__.py
MdnWenjianApiZhongwenWendang/js/hooks/extensions/highlight.js
mdn_wenjian_api_zhongwen_wendang-2024.3.2.0.dist-info/METADATA
mdn_wenjian_api_zhongwen_wendang-2024.3.2.0.dist-info/WHEEL
mdn_wenjian_api_zhongwen_wendang-2024.3.2.0.dist-info/entry_points.txt
mdn_wenjian_api_zhongwen_wendang-2024.3.2.0.dist-info/top_level.txt
mdn_wenjian_api_zhongwen_wendang-2024.3.2.0.dist-info/RECORD
